README.md
setup.py
pygobject_prebuilt_deps/__init__.py
pygobject_prebuilt_deps/wheels/PyGObject-3.42.2-cp310-cp310-win32.whl
pygobject_prebuilt_deps/wheels/PyGObject-3.42.2-cp310-cp310-win_amd64.whl
pygobject_prebuilt_deps/wheels/PyGObject-3.42.2-cp37-cp37m-win32.whl
pygobject_prebuilt_deps/wheels/PyGObject-3.42.2-cp37-cp37m-win_amd64.whl
pygobject_prebuilt_deps/wheels/PyGObject-3.42.2-cp38-cp38-win32.whl
pygobject_prebuilt_deps/wheels/PyGObject-3.42.2-cp38-cp38-win_amd64.whl
pygobject_prebuilt_deps/wheels/PyGObject-3.42.2-cp39-cp39-win32.whl
pygobject_prebuilt_deps/wheels/PyGObject-3.42.2-cp39-cp39-win_amd64.whl
pygobject_prebuilt_deps/wheels/pycairo-1.21.0-cp310-cp310-win32.whl
pygobject_prebuilt_deps/wheels/pycairo-1.21.0-cp310-cp310-win_amd64.whl
pygobject_prebuilt_deps/wheels/pycairo-1.21.0-cp37-cp37m-win32.whl
pygobject_prebuilt_deps/wheels/pycairo-1.21.0-cp37-cp37m-win_amd64.whl
pygobject_prebuilt_deps/wheels/pycairo-1.21.0-cp38-cp38-win32.whl
pygobject_prebuilt_deps/wheels/pycairo-1.21.0-cp38-cp38-win_amd64.whl
pygobject_prebuilt_deps/wheels/pycairo-1.21.0-cp39-cp39-win32.whl
pygobject_prebuilt_deps/wheels/pycairo-1.21.0-cp39-cp39-win_amd64.whl
pygobject_prebuilt_deps/x64_vs16/bin/atk-1.0-0.dll
pygobject_prebuilt_deps/x64_vs16/bin/cairo-2.dll
pygobject_prebuilt_deps/x64_vs16/bin/cairo-gobject-2.dll
pygobject_prebuilt_deps/x64_vs16/bin/cairo-script-interpreter-2.dll
pygobject_prebuilt_deps/x64_vs16/bin/epoxy-0.dll
pygobject_prebuilt_deps/x64_vs16/bin/expat.dll
pygobject_prebuilt_deps/x64_vs16/bin/ffi-7.dll
pygobject_prebuilt_deps/x64_vs16/bin/fontconfig-1.dll
pygobject_prebuilt_deps/x64_vs16/bin/freetype-6.dll
pygobject_prebuilt_deps/x64_vs16/bin/fribidi-0.dll
pygobject_prebuilt_deps/x64_vs16/bin/gailutil-3-vs16.dll
pygobject_prebuilt_deps/x64_vs16/bin/gdk-3-vs16.dll
pygobject_prebuilt_deps/x64_vs16/bin/gdk_pixbuf-2.0-0.dll
pygobject_prebuilt_deps/x64_vs16/bin/gio-2.0-0.dll
pygobject_prebuilt_deps/x64_vs16/bin/girepository-1.0-1.dll
pygobject_pycairo_prebuilt_libraries_vs2019.egg-info/PKG-INFO
pygobject_pycairo_prebuilt_libraries_vs2019.egg-info/SOURCES.txt
pygobject_pycairo_prebuilt_libraries_vs2019.egg-info/dependency_links.txt
pygobject_pycairo_prebuilt_libraries_vs2019.egg-info/top_level.txt