Metadata-Version: 2.1
Name: pygobject-pycairo-prebuilt-libraries-vs2019
Version: 0.1.1a6
Summary: PyGBject PyCairo prebuilt libraries on vs2019
Home-page: https://github.com/dzhsurf/pygobject-pycairo-prebuilt-libraries-vs2019
Author: dzhsurf
Author-email: dzhsurf@gmail.com
Maintainer: dzhsurf
Maintainer-email: dzhsurf@gmail.com
License: UNKNOWN
Platform: UNKNOWN
Requires-Python: >=3.7
